bec_client/__init__.py
bec_client/beamline_mixin.py
bec_client/bec_ipython_client.py
bec_client/bec_magics.py
bec_client/bec_startup.py
bec_client/main.py
bec_client/prettytable.py
bec_client/progressbar.py
bec_client/signals.py
bec_client/callbacks/__init__.py
bec_client/callbacks/ipython_live_updates.py
bec_client/callbacks/live_table.py
bec_client/callbacks/move_device.py
bec_client/callbacks/scan_progress.py
bec_client/callbacks/utils.py
bec_client/high_level_interfaces/__init__.py
bec_client/high_level_interfaces/bec_hli.py
bec_client/high_level_interfaces/spec_hli.py
bec_client/plugins/__init__.py
bec_client/plugins/LamNI/__init__.py
bec_client/plugins/LamNI/lamni_optics_mixin.py
bec_client/plugins/LamNI/load_additional_correction.py
bec_client/plugins/LamNI/x_ray_eye_align.py
bec_client/plugins/SLS/__init__.py
bec_client/plugins/SLS/sls_info.py
bec_client/plugins/XTreme/__init__.py
bec_client/plugins/XTreme/x-treme.py
bec_client/plugins/cSAXS/__init__.py
bec_client/plugins/cSAXS/beamline_info.py
bec_client/plugins/cSAXS/cSAXS_beamline.py
bec_client/plugins/cSAXS/csaxs_bl_checks.py
bec_client/plugins/flomni/__init__.py
bec_client/plugins/flomni/flomni.py
bec_client/plugins/flomni/flomni_optics_mixin.py
bec_client/plugins/flomni/x_ray_eye_align.py
bec_client-2.4.1.dist-info/METADATA
bec_client-2.4.1.dist-info/WHEEL
bec_client-2.4.1.dist-info/entry_points.txt
bec_client-2.4.1.dist-info/top_level.txt
bec_client-2.4.1.dist-info/RECORD
